CHANGES.txt
README.txt
pypi_upload.sh
setup.py
collective/__init__.py
collective.autoresizetextarea.egg-info/PKG-INFO
collective.autoresizetextarea.egg-info/SOURCES.txt
collective.autoresizetextarea.egg-info/dependency_links.txt
collective.autoresizetextarea.egg-info/entry_points.txt
collective.autoresizetextarea.egg-info/namespace_packages.txt
collective.autoresizetextarea.egg-info/not-zip-safe
collective.autoresizetextarea.egg-info/requires.txt
collective.autoresizetextarea.egg-info/top_level.txt
collective/autoresizetextarea/__init__.py
collective/autoresizetextarea/configure.zcml
collective/autoresizetextarea/tests.py
collective/autoresizetextarea/javascripts/autoresize.jquery.min.js
collective/autoresizetextarea/javascripts/autoresize.js
collective/autoresizetextarea/profiles/default/jsregistry.xml
collective/autoresizetextarea/profiles/default/metadata.xml
docs/INSTALL.txt
docs/LICENSE.GPL
docs/LICENSE.txt