Metadata-Version: 1.0
Name: collective.autoresizetextarea
Version: 1.0b2
Summary: jQuery textarea auto-resizer for Plone.
Home-page: http://pypi.python.org/pypi/collective.autoresizetextarea
Author: Timo Stollenwerk
Author-email: timo@zmag.de
License: GPL
Keywords: jQuery textarea auto-resize
Platform: UNKNOWN
Classifier: Framework :: Plone
Classifier: Programming Language :: Python
Classifier: Topic :: Software Development :: Libraries :: Python Modules
